Workbook

Sheet Raw Data
A1: Café Sales Analysis Dashboard
A2: ID | B2: Date | C2: Product | D2: Category | E2: Quantity | F2: Unit Price | G2: Payment | H2: Customer | I2: Revenue
A3: TR001 | B3: 46025 | C3: Iced Coffee | D3: Beverage | E3: 2 | F3: 18000 | G3: QRIS | H3: Regular | I3: =SUM(E3*F3) -> 36000
A4: TR002 | B4: 46025 | C4: Croissant | D4: Food | E4: 1 | F4: 22000 | G4: CASH | H4: New | I4: =SUM(E4*F4) -> 22000
A5: TR003 | B5: 46027 | C5: Matcha Latte | D5: Beverage | E5: 1 | F5: 24000 | G5: QRIS | H5: New | I5: =SUM(E5*F5) -> 24000
A6: TR004 | B6: 46028 | C6: Iced Coffee | D6: Beverage | E6: 3 | F6: 18000 | G6: Debit | H6: Regular | I6: =SUM(E6*F6) -> 54000
A7: TR005 | B7: 46030 | C7: Chocolate Cake | D7: Food | E7: 1 | F7: 28000 | G7: QRIS | H7: Regular | I7: =SUM(E7*F7) -> 28000
A8: TR006 | B8: 46032 | C8: French Fries | D8: Food | E8: 2 | F8: 20000 | G8: CASH | H8: New | I8: =SUM(E8*F8) -> 40000
A9: TR007 | B9: 46034 | C9: Matcha Latte | D9: Beverage | E9: 2 | F9: 24000 | G9: QRIS | H9: Regular | I9: =SUM(E9*F9) -> 48000
A10: TR008 | B10: 46036 | C10: Iced Tea | D10: Beverage | E10: 2 | F10: 12000 | G10: CASH | H10: New | I10: =SUM(E10*F10) -> 24000
A11: TR009 | B11: 46039 | C11: Croissant | D11: Food | E11: 2 | F11: 22000 | G11: QRIS | H11: Regular | I11: =SUM(E11*F11) -> 44000
A12: TR010 | B12: 46041 | C12: Iced Coffee | D12: Beverage | E12: 1 | F12: 18000 | G12: Debit | H12: New | I12: =SUM(E12*F12) -> 18000
A13: TR011 | B13: 46055 | C13: Matcha Latte | D13: Beverage | E13: 3 | F13: 24000 | G13: QRIS | H13: Regular | I13: =SUM(E13*F13) -> 72000
A14: TR012 | B14: 46057 | C14: Chocolate Cake | D14: Food | E14: 2 | F14: 28000 | G14: QRIS | H14: New | I14: =SUM(E14*F14) -> 56000
... A32: TR030 | B32: 46106 | C32: Iced Tea | D32: Beverage | E32: 2 | F32: 12000 | G32: CASH | H32: Regular | I32: =SUM(E32*F32) -> 24000

Sheet Analysis
A1: CAFÉ SALES ANALYSIS
A3: Total Revenue | B3: Total Quantity Sold | C3: Total Transactions | D3: Average Transaction Value | E3: Higest Transaction | F3: Lowest Transaction
A4: =SUM('Raw Data'!I3:I32) -> 1228000 | B4: =SUM('Raw Data'!E3:E32) -> 64 | C4: =COUNTA('Raw Data'!A3:A32) -> 30 | D4: =AVERAGE('Raw Data'!I3:I32) -> 40933.333 | E4: =MAX('Raw Data'!I3:I32) -> 72000 | F4: =MIN('Raw Data'!I3:I32) -> 18000
A6: PRODUCT ANALYSIS
A7: Product | B7: Total Qty | C7: Total Revenue
A8: Iced Coffee | B8: =SUMIF('Raw Data'!C3:C32, A8, 'Raw Data'!E3:E32) -> 17 | C8: =SUMIF('Raw Data'!C3:C32, Analysis!A8, 'Raw Data'!I3:I32) -> 306000
A9: Croissant | B9: =SUMIF('Raw Data'!C4:C33, A9, 'Raw Data'!E4:E33) -> 9 | C9: =SUMIF('Raw Data'!C4:C33, Analysis!A9, 'Raw Data'!I4:I33) -> 198000
A10: Matcha Latte | B10: =SUMIF('Raw Data'!C5:C34, A10, 'Raw Data'!E5:E34) -> 11 | C10: =SUMIF('Raw Data'!C5:C34, Analysis!A10, 'Raw Data'!I5:I34) -> 264000
A11: Chocolate Cake | B11: =SUMIF('Raw Data'!C7:C36, A11, 'Raw Data'!E7:E36) -> 6 | C11: =SUMIF('Raw Data'!C7:C36, Analysis!A11, 'Raw Data'!I7:I36) -> 168000
A12: French Fries | B12: =SUMIF('Raw Data'!C8:C37, A12, 'Raw Data'!E8:E37) -> 5 | C12: =SUMIF('Raw Data'!C8:C37, Analysis!A12, 'Raw Data'!I8:I37) -> 100000
A13: Iced Tea | B13: =SUMIF('Raw Data'!C9:C38, A13, 'Raw Data'!E9:E38) -> 16 | C13: =SUMIF('Raw Data'!C9:C38, Analysis!A13, 'Raw Data'!I9:I38) -> 192000
A15: CATEGORY ANALYSIS
A16: Category | B16: Total Qty | C16: Total Revenue
A17: Beverage | B17: =SUMIF('Raw Data'!D3:D32, Analysis!A17, 'Raw Data'!E3:E32) -> 44 | C17: =SUMIF('Raw Data'!D3:D32, Analysis!A17, 'Raw Data'!I3:I32) -> 762000
A18: Food | B18: =SUMIF('Raw Data'!D3:D32, Analysis!A18, 'Raw Data'!E3:E32) -> 20 | C18: =SUMIF('Raw Data'!D4:D33, Analysis!A18, 'Raw Data'!I4:I33) -> 466000
A20: MONTHLY ANALYSIS
A21: Month | B21: Transactions | C21: Revenue
A22: January | B22: =COUNTIFS('Raw Data'!B3:B32,">="&DATE(2026,1,1),'Raw Data'!B3:B32,"<"&DATE(2026,2,1)) -> 10 | C22: =SUMIFS('Raw Data'!I3:I32,'Raw Data'!B3:B32,">="&DATE(2026,1,1),'Raw Data'!B3:B32,"<"&DATE(2026,2,1)) -> 338000
A23: February | B23: =COUNTIFS('Raw Data'!B3:B32,">="&DATE(2026,2,1),'Raw Data'!B3:B32,"<"&DATE(2026,3,1)) -> 10 | C23: =SUMIFS('Raw Data'!I3:I32,'Raw Data'!B3:B32,">="&DATE(2026,2,1),'Raw Data'!B3:B32,"<"&DATE(2026,3,1)) -> 438000
A24: March | B24: =COUNTIFS('Raw Data'!B3:B32,">="&DATE(2026,3,1),'Raw Data'!B3:B32,"<"&DATE(2026,4,1)) -> 10 | C24: =SUMIFS('Raw Data'!I3:I32,'Raw Data'!B3:B32,">="&DATE(2026,3,1),'Raw Data'!B3:B32,"<"&DATE(2026,4,1)) -> 452000
A26: PAYMENT ANALYSIS
A27: Payment Method | B27: Transactions | C27: Revenue
A28: QRIS | B28: =COUNTIF('Raw Data'!G3:G32, Analysis!A28) -> 15 | C28: =SUMIF('Raw Data'!G3:G32, A28, 'Raw Data'!I3:I32) -> 654000
A29: CASH | B29: =COUNTIF('Raw Data'!G4:G33, Analysis!A29) -> 9 | C29: =SUMIF('Raw Data'!G4:G33, A29, 'Raw Data'!I4:I33) -> 310000
A30: Debit | B30: =COUNTIF('Raw Data'!G5:G34, Analysis!A30) -> 6 | C30: =SUMIF('Raw Data'!G5:G34, A30, 'Raw Data'!I5:I34) -> 264000
A32: CUSTOMER ANALYSIS
A33: Customer Type | B33: Transactions | C33: Revenue
A34: New | B34: =COUNTIF('Raw Data'!H3:H32, Analysis!A34) -> 13 | C34: =SUMIF('Raw Data'!H3:H32, Analysis!A34, 'Raw Data'!I3:I32) -> 398000
A35: Regular | B35: =COUNTIF('Raw Data'!H3:H32,Analysis!A35) -> 17 | C35: =SUMIF('Raw Data'!H3:H32, Analysis!A35, 'Raw Data'!I3:I32) -> 830000
